LICENSE
MANIFEST.in
README.md
setup.py
expo/__init__.py
expo/__main__.py
expo/banner.txt
expo/events.py
expo/py.typed
expo/state.py
expo/api/__init__.py
expo/api/gateway.py
expo/api/voice.py
expo/commands/__init__.py
expo/commands/_types.py
expo/commands/bot.py
expo/commands/cog.py
expo/commands/context.py
expo/commands/core.py
expo/commands/errors.py
expo/commands/help.py
expo/commands/app/__init__.py
expo/internal/opus.py
expo/ipc/__init__.py
expo/ipc/client.py
expo/ipc/server.py
expo/ui/__init__.py
expo/ui/interaction.py
expo/ui/item.py
expo/ui/view.py
hikari_expo.egg-info/PKG-INFO
hikari_expo.egg-info/SOURCES.txt
hikari_expo.egg-info/dependency_links.txt
hikari_expo.egg-info/requires.txt
hikari_expo.egg-info/top_level.txt