Metadata-Version: 2.1
Name: hikari-expo
Version: 1.1.0
Summary: Extension module for hikari
Home-page: UNKNOWN
Author: VincentRPS
License: UNKNOWN
Platform: UNKNOWN
Classifier: Typing :: Typed
Classifier: Framework :: aiohttp
Classifier: Framework :: AsyncIO
Classifier: Development Status :: 2 - Pre-Alpha
Classifier: Programming Language :: Python :: 3
Classifier: Programming Language :: Python :: 3 :: Only
Classifier: License :: OSI Approved :: Apache Software License
Requires: hikari
Provides-Extra: docs
License-File: LICENSE
